{
  "subjects": [
    {
      "episodes_info": "",
      "rate": "7.7",
      "cover_x": 1461,
      "title": "正义回廊",
      "url": "https://movie.douban.com/subject/35311878/",
      "playable": false,
      "cover": "https://img9.doubanio.com/view/photo/s_ratio_poster/public/p2883864814.jpg",
      "id": "35311878",
      "cover_y": 2048,
      "is_new": false
    },
    {
      "episodes_info": "",
      "rate": "7.8",
      "cover_x": 2898,
      "title": "千寻小姐",
      "url": "https://movie.douban.com/subject/35791966/",
      "playable": false,
      "cover": "https://img2.doubanio.com/view/photo/s_ratio_poster/public/p2884868812.jpg",
      "id": "35791966",
      "cover_y": 4096,
      "is_new": false
    },
    {
      "episodes_info": "",
      "rate": "6.8",
      "cover_x": 2835,
      "title": "巴黎记忆",
      "url": "https://movie.douban.com/subject/35238572/",
      "playable": false,
      "cover": "https://img2.doubanio.com/view/photo/s_ratio_poster/public/p2876041341.jpg",
      "id": "35238572",
      "cover_y": 3850,
      "is_new": true
    },
    {
      "episodes_info": "",
      "rate": "5.1",
      "cover_x": 945,
      "title": "交换人生",
      "url": "https://movie.douban.com/subject/35513968/",
      "playable": true,
      "cover": "https://img1.doubanio.com/view/photo/s_ratio_poster/public/p2886396440.jpg",
      "id": "35513968",
      "cover_y": 1341,
      "is_new": false
    },
    {
      "episodes_info": "",
      "rate": "8.0",
      "cover_x": 1440,
      "title": "鲸",
      "url": "https://movie.douban.com/subject/35312421/",
      "playable": false,
      "cover": "https://img2.doubanio.com/view/photo/s_ratio_poster/public/p2885153371.jpg",
      "id": "35312421",
      "cover_y": 2048,
      "is_new": false
    },
    {
      "episodes_info": "",
      "rate": "8.0",
      "cover_x": 5000,
      "title": "巴比伦",
      "url": "https://movie.douban.com/subject/34467461/",
      "playable": false,
      "cover": "https://img1.doubanio.com/view/photo/s_ratio_poster/public/p2884457470.jpg",
      "id": "34467461",
      "cover_y": 7407,
      "is_new": false
    },
    {
      "episodes_info": "",
      "rate": "7.7",
      "cover_x": 2000,
      "title": "生无可恋的奥托",
      "url": "https://movie.douban.com/subject/27150277/",
      "playable": false,
      "cover": "https://img9.doubanio.com/view/photo/s_ratio_poster/public/p2888737884.jpg",
      "id": "27150277",
      "cover_y": 2964,
      "is_new": false
    },
    {
      "episodes_info": "",
      "rate": "6.7",
      "cover_x": 1080,
      "title": "行骗高手",
      "url": "https://movie.douban.com/subject/35116322/",
      "playable": false,
      "cover": "https://img1.doubanio.com/view/photo/s_ratio_poster/public/p2886396720.jpg",
      "id": "35116322",
      "cover_y": 1620,
      "is_new": false
    },
    {
      "episodes_info": "",
      "rate": "6.4",
      "cover_x": 1500,
      "title": "虽然只是弄丢了手机",
      "url": "https://movie.douban.com/subject/35203206/",
      "playable": false,
      "cover": "https://img2.doubanio.com/view/photo/s_ratio_poster/public/p2887034251.jpg",
      "id": "35203206",
      "cover_y": 2222,
      "is_new": false
    },
    {
      "episodes_info": "",
      "rate": "8.1",
      "cover_x": 2025,
      "title": "晒后假日",
      "url": "https://movie.douban.com/subject/35876302/",
      "playable": false,
      "cover": "https://img1.doubanio.com/view/photo/s_ratio_poster/public/p2880990688.jpg",
      "id": "35876302",
      "cover_y": 3000,
      "is_new": false
    },
    {
      "episodes_info": "",
      "rate": "7.9",
      "cover_x": 8784,
      "title": "铃芽之旅",
      "url": "https://movie.douban.com/subject/35371261/",
      "playable": false,
      "cover": "https://img2.doubanio.com/view/photo/s_ratio_poster/public/p2887641712.jpg",
      "id": "35371261",
      "cover_y": 12402,
      "is_new": false
    },
    {
      "episodes_info": "",
      "rate": "5.8",
      "cover_x": 1400,
      "title": "交涉",
      "url": "https://movie.douban.com/subject/33406476/",
      "playable": false,
      "cover": "https://img9.doubanio.com/view/photo/s_ratio_poster/public/p2885515624.jpg",
      "id": "33406476",
      "cover_y": 2015,
      "is_new": false
    },
    {
      "episodes_info": "",
      "rate": "8.2",
      "cover_x": 2920,
      "title": "鱼之子",
      "url": "https://movie.douban.com/subject/35797506/",
      "playable": false,
      "cover": "https://img9.doubanio.com/view/photo/s_ratio_poster/public/p2884266466.jpg",
      "id": "35797506",
      "cover_y": 4128,
      "is_new": false
    },
    {
      "episodes_info": "",
      "rate": "7.9",
      "cover_x": 1334,
      "title": "伊尼舍林的报丧女妖",
      "url": "https://movie.douban.com/subject/34969348/",
      "playable": false,
      "cover": "https://img1.doubanio.com/view/photo/s_ratio_poster/public/p2877252828.jpg",
      "id": "34969348",
      "cover_y": 2000,
      "is_new": false
    },
    {
      "episodes_info": "",
      "rate": "5.4",
      "cover_x": 2500,
      "title": "黑豹2",
      "url": "https://movie.douban.com/subject/30167997/",
      "playable": false,
      "cover": "https://img9.doubanio.com/view/photo/s_ratio_poster/public/p2888100744.jpg",
      "id": "30167997",
      "cover_y": 3703,
      "is_new": false
    },
    {
      "episodes_info": "",
      "rate": "7.2",
      "cover_x": 1080,
      "title": "女人们的谈话",
      "url": "https://movie.douban.com/subject/35290372/",
      "playable": false,
      "cover": "https://img1.doubanio.com/view/photo/s_ratio_poster/public/p2885120950.jpg",
      "id": "35290372",
      "cover_y": 1600,
      "is_new": false
    },
    {
      "episodes_info": "",
      "rate": "6.0",
      "cover_x": 3158,
      "title": "梅根",
      "url": "https://movie.douban.com/subject/30277290/",
      "playable": false,
      "cover": "https://img2.doubanio.com/view/photo/s_ratio_poster/public/p2887950831.jpg",
      "id": "30277290",
      "cover_y": 5000,
      "is_new": false
    },
    {
      "episodes_info": "",
      "rate": "7.1",
      "cover_x": 2800,
      "title": "夜枭",
      "url": "https://movie.douban.com/subject/35587790/",
      "playable": false,
      "cover": "https://img2.doubanio.com/view/photo/s_ratio_poster/public/p2882458713.jpg",
      "id": "35587790",
      "cover_y": 4000,
      "is_new": false
    },
    {
      "episodes_info": "",
      "rate": "8.6",
      "cover_x": 1080,
      "title": "乐土",
      "url": "https://movie.douban.com/subject/35870056/",
      "playable": false,
      "cover": "https://img9.doubanio.com/view/photo/s_ratio_poster/public/p2881033774.jpg",
      "id": "35870056",
      "cover_y": 1600,
      "is_new": false
    },
    {
      "episodes_info": "",
      "rate": "9.9",
      "cover_x": 847,
      "title": "羽生结弦冰上物语2023 礼物",
      "url": "https://movie.douban.com/subject/36245702/",
      "playable": false,
      "cover": "https://img2.doubanio.com/view/photo/s_ratio_poster/public/p2888743242.jpg",
      "id": "36245702",
      "cover_y": 1200,
      "is_new": true
    },
    {
      "episodes_info": "",
      "rate": "7.5",
      "cover_x": 1500,
      "title": "沼泽深处的女孩",
      "url": "https://movie.douban.com/subject/35230876/",
      "playable": true,
      "cover": "https://img2.doubanio.com/view/photo/s_ratio_poster/public/p2883601331.jpg",
      "id": "35230876",
      "cover_y": 2224,
      "is_new": false
    },
    {
      "episodes_info": "",
      "rate": "6.2",
      "cover_x": 2000,
      "title": "想见你",
      "url": "https://movie.douban.com/subject/35208467/",
      "playable": true,
      "cover": "https://img1.doubanio.com/view/photo/s_ratio_poster/public/p2885427348.jpg",
      "id": "35208467",
      "cover_y": 3000,
      "is_new": false
    },
    {
      "episodes_info": "",
      "rate": "8.1",
      "cover_x": 1170,
      "title": "亲密",
      "url": "https://movie.douban.com/subject/35205617/",
      "playable": false,
      "cover": "https://img1.doubanio.com/view/photo/s_ratio_poster/public/p2888877769.jpg",
      "id": "35205617",
      "cover_y": 1664,
      "is_new": false
    },
    {
      "episodes_info": "",
      "rate": "7.6",
      "cover_x": 2897,
      "title": "今夜，就算这份爱恋从世界上消失",
      "url": "https://movie.douban.com/subject/35772573/",
      "playable": false,
      "cover": "https://img1.doubanio.com/view/photo/s_ratio_poster/public/p2871137380.jpg",
      "id": "35772573",
      "cover_y": 4096,
      "is_new": false
    },
    {
      "episodes_info": "",
      "rate": "6.6",
      "cover_x": 750,
      "title": "在公交车站直到黎明",
      "url": "https://movie.douban.com/subject/35919112/",
      "playable": false,
      "cover": "https://img1.doubanio.com/view/photo/s_ratio_poster/public/p2875219039.jpg",
      "id": "35919112",
      "cover_y": 1059,
      "is_new": true
    },
    {
      "episodes_info": "",
      "rate": "7.5",
      "cover_x": 2362,
      "title": "晨光正好",
      "url": "https://movie.douban.com/subject/35211730/",
      "playable": false,
      "cover": "https://img1.doubanio.com/view/photo/s_ratio_poster/public/p2880259607.jpg",
      "id": "35211730",
      "cover_y": 3209,
      "is_new": false
    },
    {
      "episodes_info": "",
      "rate": "7.4",
      "cover_x": 1800,
      "title": "塔尔",
      "url": "https://movie.douban.com/subject/35430833/",
      "playable": false,
      "cover": "https://img9.doubanio.com/view/photo/s_ratio_poster/public/p2883951104.jpg",
      "id": "35430833",
      "cover_y": 2570,
      "is_new": false
    },
    {
      "episodes_info": "",
      "rate": "8.5",
      "cover_x": 1000,
      "title": "西线无战事",
      "url": "https://movie.douban.com/subject/3042261/",
      "playable": false,
      "cover": "https://img9.doubanio.com/view/photo/s_ratio_poster/public/p2879787106.jpg",
      "id": "3042261",
      "cover_y": 1500,
      "is_new": false
    },
    {
      "episodes_info": "",
      "rate": "7.5",
      "cover_x": 1895,
      "title": "造梦之家",
      "url": "https://movie.douban.com/subject/35390098/",
      "playable": false,
      "cover": "https://img9.doubanio.com/view/photo/s_ratio_poster/public/p2885995265.jpg",
      "id": "35390098",
      "cover_y": 3000,
      "is_new": false
    },
    {
      "episodes_info": "",
      "rate": "7.4",
      "cover_x": 4429,
      "title": "还是觉得你最好",
      "url": "https://movie.douban.com/subject/35503125/",
      "playable": true,
      "cover": "https://img2.doubanio.com/view/photo/s_ratio_poster/public/p2879301401.jpg",
      "id": "35503125",
      "cover_y": 6201,
      "is_new": false
    },
    {
      "episodes_info": "",
      "rate": "7.8",
      "cover_x": 1284,
      "title": "核磁共振",
      "url": "https://movie.douban.com/subject/35699754/",
      "playable": false,
      "cover": "https://img1.doubanio.com/view/photo/s_ratio_poster/public/p2872932287.jpg",
      "id": "35699754",
      "cover_y": 1856,
      "is_new": false
    },
    {
      "episodes_info": "",
      "rate": "5.8",
      "cover_x": 1500,
      "title": "我们有鬼啦",
      "url": "https://movie.douban.com/subject/27594861/",
      "playable": false,
      "cover": "https://img2.doubanio.com/view/photo/s_ratio_poster/public/p2887036542.jpg",
      "id": "27594861",
      "cover_y": 2222,
      "is_new": true
    },
    {
      "episodes_info": "",
      "rate": "7.2",
      "cover_x": 2100,
      "title": "上帝的笔误",
      "url": "https://movie.douban.com/subject/35358584/",
      "playable": false,
      "cover": "https://img2.doubanio.com/view/photo/s_ratio_poster/public/p2877741323.jpg",
      "id": "35358584",
      "cover_y": 3000,
      "is_new": false
    },
    {
      "episodes_info": "",
      "rate": "7.6",
      "cover_x": 1187,
      "title": "分手的决心",
      "url": "https://movie.douban.com/subject/35073886/",
      "playable": false,
      "cover": "https://img2.doubanio.com/view/photo/s_ratio_poster/public/p2873816122.jpg",
      "id": "35073886",
      "cover_y": 1701,
      "is_new": false
    },
    {
      "episodes_info": "",
      "rate": "8.1",
      "cover_x": 3158,
      "title": "穿靴子的猫2",
      "url": "https://movie.douban.com/subject/25868125/",
      "playable": false,
      "cover": "https://img1.doubanio.com/view/photo/s_ratio_poster/public/p2885032978.jpg",
      "id": "25868125",
      "cover_y": 5000,
      "is_new": false
    },
    {
      "episodes_info": "",
      "rate": "7.4",
      "cover_x": 1536,
      "title": "短暂的偷情纪实",
      "url": "https://movie.douban.com/subject/35447469/",
      "playable": false,
      "cover": "https://img9.doubanio.com/view/photo/s_ratio_poster/public/p2877773686.jpg",
      "id": "35447469",
      "cover_y": 2048,
      "is_new": false
    },
    {
      "episodes_info": "",
      "rate": "8.1",
      "cover_x": 904,
      "title": "地狱尖兵",
      "url": "https://movie.douban.com/subject/36118263/",
      "playable": false,
      "cover": "https://img1.doubanio.com/view/photo/s_ratio_poster/public/p2881661637.jpg",
      "id": "36118263",
      "cover_y": 1280,
      "is_new": false
    },
    {
      "episodes_info": "",
      "rate": "6.4",
      "cover_x": 1334,
      "title": "菜单",
      "url": "https://movie.douban.com/subject/30455615/",
      "playable": false,
      "cover": "https://img9.doubanio.com/view/photo/s_ratio_poster/public/p2880339524.jpg",
      "id": "30455615",
      "cover_y": 2000,
      "is_new": false
    },
    {
      "episodes_info": "",
      "rate": "7.5",
      "cover_x": 3000,
      "title": "悲情三角",
      "url": "https://movie.douban.com/subject/27066152/",
      "playable": false,
      "cover": "https://img9.doubanio.com/view/photo/s_ratio_poster/public/p2880467086.jpg",
      "id": "27066152",
      "cover_y": 4451,
      "is_new": false
    },
    {
      "episodes_info": "",
      "rate": "7.6",
      "cover_x": 8699,
      "title": "瞬息全宇宙",
      "url": "https://movie.douban.com/subject/30314848/",
      "playable": false,
      "cover": "https://img9.doubanio.com/view/photo/s_ratio_poster/public/p2869765076.jpg",
      "id": "30314848",
      "cover_y": 12599,
      "is_new": false
    },
    {
      "episodes_info": "",
      "rate": "7.3",
      "cover_x": 1635,
      "title": "珀尔",
      "url": "https://movie.douban.com/subject/35801819/",
      "playable": false,
      "cover": "https://img1.doubanio.com/view/photo/s_ratio_poster/public/p2880319580.jpg",
      "id": "35801819",
      "cover_y": 2413,
      "is_new": false
    },
    {
      "episodes_info": "",
      "rate": "8.5",
      "cover_x": 1944,
      "title": "十三条命",
      "url": "https://movie.douban.com/subject/35056243/",
      "playable": false,
      "cover": "https://img2.doubanio.com/view/photo/s_ratio_poster/public/p2877798713.jpg",
      "id": "35056243",
      "cover_y": 2880,
      "is_new": false
    },
    {
      "episodes_info": "",
      "rate": "7.3",
      "cover_x": 964,
      "title": "误杀瞒天记2",
      "url": "https://movie.douban.com/subject/36056562/",
      "playable": false,
      "cover": "https://img1.doubanio.com/view/photo/s_ratio_poster/public/p2886115690.jpg",
      "id": "36056562",
      "cover_y": 1350,
      "is_new": false
    },
    {
      "episodes_info": "",
      "rate": "8.6",
      "cover_x": 1403,
      "title": "宿敌",
      "url": "https://movie.douban.com/subject/35882880/",
      "playable": false,
      "cover": "https://img9.doubanio.com/view/photo/s_ratio_poster/public/p2874026114.jpg",
      "id": "35882880",
      "cover_y": 2048,
      "is_new": false
    },
    {
      "episodes_info": "",
      "rate": "6.6",
      "cover_x": 750,
      "title": "百花",
      "url": "https://movie.douban.com/subject/35524883/",
      "playable": false,
      "cover": "https://img1.doubanio.com/view/photo/s_ratio_poster/public/p2874984730.jpg",
      "id": "35524883",
      "cover_y": 1061,
      "is_new": false
    },
    {
      "episodes_info": "",
      "rate": "6.6",
      "cover_x": 1500,
      "title": "利刃出鞘2",
      "url": "https://movie.douban.com/subject/34939037/",
      "playable": false,
      "cover": "https://img2.doubanio.com/view/photo/s_ratio_poster/public/p2882492021.jpg",
      "id": "34939037",
      "cover_y": 2222,
      "is_new": false
    },
    {
      "episodes_info": "",
      "rate": "6.2",
      "cover_x": 1080,
      "title": "母性",
      "url": "https://movie.douban.com/subject/35656754/",
      "playable": false,
      "cover": "https://img9.doubanio.com/view/photo/s_ratio_poster/public/p2874159116.jpg",
      "id": "35656754",
      "cover_y": 1528,
      "is_new": true
    },
    {
      "episodes_info": "",
      "rate": "7.8",
      "cover_x": 2000,
      "title": "子弹列车",
      "url": "https://movie.douban.com/subject/35118954/",
      "playable": false,
      "cover": "https://img2.doubanio.com/view/photo/s_ratio_poster/public/p2873950053.jpg",
      "id": "35118954",
      "cover_y": 2964,
      "is_new": false
    },
    {
      "episodes_info": "",
      "rate": "5.7",
      "cover_x": 2764,
      "title": "魔力麦克3：最后之舞",
      "url": "https://movie.douban.com/subject/35680805/",
      "playable": false,
      "cover": "https://img1.doubanio.com/view/photo/s_ratio_poster/public/p2885389768.jpg",
      "id": "35680805",
      "cover_y": 4096,
      "is_new": true
    },
    {
      "episodes_info": "",
      "rate": "6.8",
      "cover_x": 2593,
      "title": "光之帝国",
      "url": "https://movie.douban.com/subject/35423787/",
      "playable": false,
      "cover": "https://img9.doubanio.com/view/photo/s_ratio_poster/public/p2878741754.jpg",
      "id": "35423787",
      "cover_y": 3840,
      "is_new": false
    }
  ]
}